maleo/metadata/client/__init__.py
maleo/metadata/client/config.py
maleo/metadata/client/manager.py
maleo/metadata/client/services/__init__.py
maleo/metadata/client/services/blood_type.py
maleo/metadata/client/services/gender.py
maleo/metadata/client/services/medical_role.py
maleo/metadata/client/services/medical_service.py
maleo/metadata/client/services/organization_role.py
maleo/metadata/client/services/organization_type.py
maleo/metadata/client/services/service.py
maleo/metadata/client/services/system_role.py
maleo/metadata/client/services/user_type.py
maleo_metadata_client-0.12.5.dist-info/licenses/LICENSE
maleo_metadata_client-0.12.5.dist-info/METADATA
maleo_metadata_client-0.12.5.dist-info/WHEEL
maleo_metadata_client-0.12.5.dist-info/top_level.txt
maleo_metadata_client-0.12.5.dist-info/RECORD
